demo/__init__.py
demo/demo.py
materials_lib/__init__.py
materials_lib/force.py
materials_lib/material.py
materials_lib/shapes.py
materials_lib/torque.py
materials_lib/units.py
materials_lib-0.8.4.dist-info/LICENSE
materials_lib-0.8.4.dist-info/METADATA
materials_lib-0.8.4.dist-info/WHEEL
materials_lib-0.8.4.dist-info/top_level.txt
materials_lib-0.8.4.dist-info/RECORD
