Metadata-Version: 2.1
Name: materials-lib
Version: 0.8.4
Summary: Open and configurable materials library for Python.
Author: John Halazonetis
Author-email: <john.halazonetis@icloud.com>
Project-URL: Repository, https://gitlab.com/johnhal/materials-python
Keywords: python,materials
Classifier: Intended Audience :: Developers
Classifier: Programming Language :: Python :: 3
Classifier: Operating System :: Unix
Classifier: Operating System :: MacOS :: MacOS X
Classifier: Operating System :: Microsoft :: Windows
License-File: LICENSE
Requires-Dist: toml
Requires-Dist: pathlib
Requires-Dist: pint
